aeromaps/__init__.py
aeromaps/core/__init__.py
aeromaps/core/cli.py
aeromaps/core/gemseo.py
aeromaps/core/models.py
aeromaps/core/process.py
aeromaps/gui/__init__.py
aeromaps/gui/config.yaml
aeromaps/gui/graphical_user_interface.py
aeromaps/gui/gui.ipynb
aeromaps/gui/plots.py
aeromaps/gui/resources/Beta.png
aeromaps/gui/resources/aboutAeroMAPS_en.md
aeromaps/gui/resources/aboutAeroMAPS_fr.md
aeromaps/gui/resources/logo-ISAE_SUPAERO.png
aeromaps/models/__init__.py
aeromaps/models/air_transport/__init__.py
aeromaps/models/air_transport/air_traffic/__init__.py
aeromaps/models/air_transport/air_traffic/ask.py
aeromaps/models/air_transport/air_traffic/price_elasticity.py
aeromaps/models/air_transport/air_traffic/rpk.py
aeromaps/models/air_transport/air_traffic/rtk.py
aeromaps/models/air_transport/air_traffic/short_range_distribution.py
aeromaps/models/air_transport/air_traffic/total_aircraft_distance.py
aeromaps/models/air_transport/aircraft_fleet_and_operations/__init__.py
aeromaps/models/air_transport/aircraft_fleet_and_operations/aircraft_fleet_and_operations.py
aeromaps/models/air_transport/aircraft_fleet_and_operations/fleet/__init__.py
aeromaps/models/air_transport/aircraft_fleet_and_operations/fleet/aircraft_efficiency.py
aeromaps/models/air_transport/aircraft_fleet_and_operations/fleet/fleet_model.py
aeromaps/models/air_transport/aircraft_fleet_and_operations/fleet/fleet_numeric.py
aeromaps/models/air_transport/aircraft_fleet_and_operations/load_factor/__init__.py
aeromaps/models/air_transport/aircraft_fleet_and_operations/load_factor/load_factor.py
aeromaps/models/air_transport/aircraft_fleet_and_operations/non_co2/__init__.py
aeromaps/models/air_transport/aircraft_fleet_and_operations/non_co2/non_co2.py
aeromaps/models/air_transport/aircraft_fleet_and_operations/operations/__init__.py
aeromaps/models/air_transport/aircraft_fleet_and_operations/operations/operations.py
aeromaps/models/air_transport/constants.py
aeromaps/models/base.py
aeromaps-1.0.0.dist-info/COPYING
aeromaps-1.0.0.dist-info/METADATA
aeromaps-1.0.0.dist-info/WHEEL
aeromaps-1.0.0.dist-info/entry_points.txt
aeromaps-1.0.0.dist-info/RECORD
