Metadata-Version: 2.1
Name: aeromaps
Version: 1.0.0
Summary: AeroMAPS: Multidisciplinary Assessment of Prospective Scenarios for air transport
Home-page: https://github.com/AeroMAPS/AeroMAPS
License: GPL-3.0-only
Keywords: air transport,climate change,prospective scenarios,energy issues
Author: Thomas PLANES
Author-email: thomas.planes@isae-supaero.fr
Requires-Python: >=3.10,<3.12
Classifier: License :: OSI Approved :: GNU General Public License v3 (GPLv3)
Classifier: Programming Language :: Python :: 3
Classifier: Programming Language :: Python :: 3.10
Classifier: Programming Language :: Python :: 3.11
Provides-Extra: lca
Requires-Dist: aenum (>=3.1.12,<4.0.0)
Requires-Dist: aerocm (==0.1.1b0)
Requires-Dist: dacite (>=1.8.0,<2.0.0)
Requires-Dist: deepdiff (>=8,<9)
Requires-Dist: dill (>=0.4.0,<0.5.0)
Requires-Dist: docstring-inheritance (>=2.0.0,<3.0.0)
Requires-Dist: gemseo (<6.3.0)
Requires-Dist: ipydatagrid (>=1.1.14,<2.0.0)
Requires-Dist: ipympl (>=0.9.3,<0.10.0)
Requires-Dist: ipysheet (>=0.5.0,<1)
Requires-Dist: ipytree (>=0.2.2,<0.3.0)
Requires-Dist: ipywidgets (>=8.0.6,<9.0.0)
Requires-Dist: jupyterlab (>=3.3.0,<4.0.0)
Requires-Dist: lca-modeller ; (python_version >= "3.10" and python_version < "3.12") and (extra == "lca")
Requires-Dist: markdown (>=3.4.3,<4.0.0)
Requires-Dist: matplotlib (>=3.7,<4.0)
Requires-Dist: numpy (>=1.20.3,<2.0.0)
Requires-Dist: openpyxl (>=3.1.2,<4.0.0)
Requires-Dist: pandas (>=1.3.0,<=2.2.2)
Requires-Dist: plotly (>=5.0.0,<6.0.0)
Requires-Dist: premise (==2.3.3) ; (python_version >= "3.10" and python_version < "3.12") and (extra == "lca")
Requires-Dist: scipy (>=1.4.1,<2.0.0)
Requires-Dist: seaborn (>=0.13.2,<0.14.0)
Requires-Dist: sympy (>=1.14.0,<2.0.0)
Requires-Dist: voila (>=0.5.0,<0.6.0)
Requires-Dist: xlrd (==1.2.0)
